[
    {
        "No": 1,
        "Destinataire": "Muriel",
        "Email": "muriel.raharison@inviso-group.com",
        "DateTime": "02/05/2024 09:11:31",
        "Status": true
    },
    {
        "No": 2,
        "Destinataire": "Harivola",
        "Email": "harivola.r@fly-technologies.com",
        "DateTime": "30/04/2024 17:10:27",
        "Status": false
    },
    {
        "No": 3,
        "Destinataire": "Muriel",
        "Email": "muriel.raharison@inviso-group.com",
        "DateTime": "02/05/2024 09:02:22",
        "Status": true
    },
    {
        "No": 4,
        "Destinataire": "Harivola",
        "Email": "harivola.r@fly-technologies.com",
        "DateTime": "30/04/2024 17:09:00",
        "Status": false
    },
    {
        "No": 5,
        "Destinataire": "Muriel",
        "Email": "muriel.raharison@inviso-group.com, muriel.raharison@inviso-group.com",
        "DateTime": "30/04/2024 17:22:36",
        "Status": true
    },
    {
        "No": 6,
        "Destinataire": "Muriel",
        "Email": "muriel.raharison@inviso-group.com, muriel.raharison@inviso-group.com",
        "DateTime": "30/04/2024 17:24:08",
        "Status": true
    },
    {
        "No": 7,
        "Destinataire": "Muriel",
        "Email": "muriel.raharison@inviso-group.com, muriel.raharison@inviso-group.com",
        "DateTime": "02/05/2024 08:41:43",
        "Status": true
    },
    {
        "No": 8,
        "Destinataire": "Muriel",
        "Email": "muriel.raharison@inviso-group.com, muriel.raharison@inviso-group.com",
        "DateTime": "02/05/2024 08:46:13",
        "Status": true
    },
    {
        "No": 9,
        "Destinataire": "Muriel",
        "Email": "muriel.raharison@inviso-group.com, muriel.raharison@inviso-group.com",
        "DateTime": "02/05/2024 09:01:30",
        "Status": true
    },
    {
        "No": 10,
        "Destinataire": "Muriel",
        "Email": "muriel.raharison@inviso-group.com, muriel.raharison@inviso-group.com",
        "DateTime": "02/05/2024 09:12:48",
        "Status": false
    },
    {
        "No": 11,
        "Destinataire": "Muriel",
        "Email": "muriel.raharison@inviso-group.com, muriel.raharison@inviso-group.com",
        "DateTime": "03/05/2024 09:39:35",
        "Status": false
    },
    {
        "No": 12,
        "Destinataire": "Muriel",
        "Email": "muriel.raharison@inviso-group.com, muriel.raharison@inviso-group.com",
        "DateTime": "03/05/2024 09:42:34",
        "Status": true
    },
    {
        "No": 13,
        "Destinataire": "Muriel",
        "Email": "muriel.raharison@inviso-group.com, muriel.raharison@inviso-group.com",
        "DateTime": "03/05/2024 09:42:23",
        "Status": true
    }
]